{
  "project_info": {
    "project_number": "905804763764",
    "project_id": "register-and-login-f0f8d",
    "storage_bucket": "register-and-login-f0f8d.appspot.com"
  },
  "client": [
    {
      "client_info": {
        "mobilesdk_app_id": "1:905804763764:android:6439b90d0a86344c3c3721",
        "android_client_info": {
          "package_name": "com.example.registerandlogin"
        }
      },
      "oauth_client": [
        {
          "client_id": "905804763764-0aua6vqdmg33b9itd972bvt54748vrd4.apps.googleusercontent.com",
          "client_type": 3
        }
      ],
      "api_key": [
        {
          "current_key": "AIzaSyD3lKTFl7e_iBm08goIXw_bsLkCN6mPBek"
        }
      ],
      "services": {
        "appinvite_service": {
          "other_platform_oauth_client": [
            {
              "client_id": "905804763764-0aua6vqdmg33b9itd972bvt54748vrd4.apps.googleusercontent.com",
              "client_type": 3
            }
          ]
        }
      }
    }
  ],
  "configuration_version": "1"
}